[
    {
        "id": 0,
        "todo": "This is only a test but editted",
        "status": false
    },
    {
        "id": 1,
        "todo": "test 3",
        "status": false
    },
    {
        "id": 2,
        "todo": "yea",
        "status": false
    },
    {
        "id": 3,
        "todo": "update again",
        "status": false
    },
    {
        "id": 4,
        "todo": "update fewgewgw",
        "status": false
    },
    {
        "id": 5,
        "todo": "This is only a test but editted",
        "status": false
    },
    {
        "id": 6,
        "todo": "update fewgewgw",
        "status": true
    },
    {
        "id": 7,
        "todo": "Edited update",
        "status": true
    },
    {
        "id": 8,
        "todo": "update again",
        "status": true
    },
    {
        "id": 9,
        "todo": "<script> alert(\"hacked you sucker\")<\/script>",
        "status": false
    }
]